simplebot_tgchan/__init__.py
simplebot_tgchan/_version.py
simplebot_tgchan/instantview.py
simplebot_tgchan/orm.py
simplebot_tgchan/subcommands.py
simplebot_tgchan/util.py
simplebot_tgchan-0.1.0.dist-info/LICENSE
simplebot_tgchan-0.1.0.dist-info/METADATA
simplebot_tgchan-0.1.0.dist-info/WHEEL
simplebot_tgchan-0.1.0.dist-info/entry_points.txt
simplebot_tgchan-0.1.0.dist-info/top_level.txt
simplebot_tgchan-0.1.0.dist-info/RECORD
