Metadata-Version: 2.1
Name: simplebot-tgchan
Version: 0.1.0
Summary: Subscribe to Telegram channels in DeltaChat.
Home-page: https://github.com/simplebot-org/simplebot_tgchan
Author: adbenitez
Author-email: adbenitez@nauta.cu
License: MPL
Keywords: simplebot plugin deltachat telegram bridge
Classifier: Development Status :: 4 - Beta
Classifier: Environment :: Plugins
Classifier: Programming Language :: Python :: 3
Classifier: License :: OSI Approved :: Mozilla Public License 2.0 (MPL 2.0)
Classifier: Operating System :: OS Independent
Classifier: Topic :: Utilities
License-File: LICENSE
Requires-Dist: simplebot (>=4.0.0)
Requires-Dist: SQLAlchemy (>=1.4.39)
Requires-Dist: Telethon (>=1.25.4)
Requires-Dist: cryptg (>=0.3.1)
Requires-Dist: Pillow (>=9.2.0)
Requires-Dist: aiohttp (>=3.8.3)
Requires-Dist: hachoir (>=3.1.3)
Provides-Extra: dev
Requires-Dist: simplebot (>=4.0.0) ; extra == 'dev'
Requires-Dist: SQLAlchemy (>=1.4.39) ; extra == 'dev'
Requires-Dist: Telethon (>=1.25.4) ; extra == 'dev'
Requires-Dist: cryptg (>=0.3.1) ; extra == 'dev'
Requires-Dist: Pillow (>=9.2.0) ; extra == 'dev'
Requires-Dist: aiohttp (>=3.8.3) ; extra == 'dev'
Requires-Dist: hachoir (>=3.1.3) ; extra == 'dev'
Requires-Dist: pytest (==7.1.3) ; extra == 'dev'
Requires-Dist: black (==22.10.0) ; extra == 'dev'
Requires-Dist: mypy (==0.982) ; extra == 'dev'
Requires-Dist: isort (==5.10.1) ; extra == 'dev'
Requires-Dist: pylint (==2.15.4) ; extra == 'dev'
Requires-Dist: pylama (==8.4.1) ; extra == 'dev'
Provides-Extra: test
Requires-Dist: pytest (==7.1.3) ; extra == 'test'
